[{"userId":4,"id":31,"title":"ullam ut quidem id aut vel consequuntur","body":"debitis eius sed quibusdam non quis consectetur vitae\nimpedit ut qui consequatur sed aut in\nquidem sit nostrum et maiores adipisci atque\nquaerat voluptatem adipisci repudiandae"},{"userId":4,"id":32,"title":"doloremque illum aliquid sunt","body":"deserunt eos nobis asperiores et hic\nest debitis repellat molestiae optio\nnihil ratione ut eos beatae quibusdam distinctio maiores\nearum voluptates et aut adipisci ea maiores voluptas maxime"}]